modelcreator/__init__.py
modelcreator/machine.py
modelcreator/metrics.py
modelcreator/models.py
modelcreator/models_generation.py
modelcreator/transformation_pipelines.py
modelcreator/transformation_utils.py
modelcreator/transformer.py
modelcreator-0.9.3.dist-info/LICENSE
modelcreator-0.9.3.dist-info/METADATA
modelcreator-0.9.3.dist-info/WHEEL
modelcreator-0.9.3.dist-info/top_level.txt
modelcreator-0.9.3.dist-info/RECORD
