Metadata-Version: 2.1
Name: modelcreator
Version: 0.9.3
Summary: Machine Learning package for quick fast model generation and comparison
Home-page: https://github.com/BartekPog/modelcreator
Author: Bartłomiej Pogodziński
Author-email: bartek.pogod@gmail.com
License: MIT
Platform: UNKNOWN
Requires-Python: >=3.6
Requires-Dist: joblib (==0.15.0)
Requires-Dist: scikit-learn (==0.23.1)
Requires-Dist: pandas (==1.0.3)
Requires-Dist: dask-ml (==1.5.0)
Requires-Dist: dask (==2.19.0)
Requires-Dist: imbalanced-learn (==0.7.0)
